<?xml version="1.0" encoding="UTF-8"?>
<libosinfo version="0.0.1">

  <os id="http://fedoraproject.org/silverblue/30">
    <short-id>silverblue30</short-id>
    <name>Fedora Silverblue 30</name>
    <version>30</version>
    <vendor>Fedora Project</vendor>
    <vendor xml:lang="ca">Projecte Fedora</vendor>
    <vendor xml:lang="de">Fedora-Projekt</vendor>
    <vendor xml:lang="es">Fedora Project</vendor>
    <vendor xml:lang="fr">Fedora Project</vendor>
    <vendor xml:lang="id">Proyek Fedora</vendor>
    <vendor xml:lang="it">Progetto Fedora</vendor>
    <vendor xml:lang="ja">Fedora Project</vendor>
    <vendor xml:lang="pl">Projekt Fedora</vendor>
    <vendor xml:lang="pt">Projecto Fedora </vendor>
    <vendor xml:lang="pt_BR">Projeto Fedora</vendor>
    <vendor xml:lang="uk">Проект Fedora</vendor>
    <family>linux</family>
    <distro>fedora</distro>
    <upgrades id="http://fedoraproject.org/silverblue/29"/>
    <derives-from id="http://fedoraproject.org/silverblue/29"/>

    <release-date>2019-04-30</release-date>

    <media arch="x86_64">
      <url>https://download.fedoraproject.org/pub/fedora/linux/releases/30/Silverblue/x86_64/iso/Fedora-Silverblue-ostree-x86_64-30-1.2.iso</url>
      <iso>
        <volume-id>Fedora-SB-ostree-x86_64-30</volume-id>
      </iso>
      <kernel>isolinux/vmlinuz</kernel>
      <initrd>isolinux/initrd.img</initrd>
    </media>

    <tree arch="x86_64">
      <url>https://download.fedoraproject.org/pub/fedora/linux/releases/30/Silverblue/x86_64/os</url>
      <treeinfo>
        <family>Fedora</family>
        <variant>Silverblue</variant>
        <version>30</version>
        <arch>x86_64</arch>
      </treeinfo>
    </tree>

    <resources arch="all">
      <minimum>
        <n-cpus>1</n-cpus>
        <cpu>1000000000</cpu>
        <ram>1073741824</ram>
        <storage>10737418240</storage>
      </minimum>

      <recommended>
        <ram>2147483648</ram>
        <storage>21474836480</storage>
      </recommended>

      <network-install>
        <ram>5368709120</ram>
      </network-install>
    </resources>

    <installer>
      <script id='http://fedoraproject.org/silverblue/kickstart/desktop'/>
    </installer>
  </os>
</libosinfo>